{"version":1,"resource":"vscode-remote://s5096657.elf.ict.griffith.edu.au:8443/var/www/html/webAppDev/Assignment1/resources/views/layouts/app.blade.php","entries":[{"id":"B8Oh.php","timestamp":1693669445558},{"id":"vP5K.php","timestamp":1693674741875},{"id":"S1Sh.php","timestamp":1693676412666},{"id":"7u1K.php","timestamp":1693711037657},{"id":"YAmx.php","source":"undoRedo.source","timestamp":1693712154451},{"id":"xxey.php","timestamp":1693894487311},{"id":"citz.php","timestamp":1694068676569},{"id":"D2bN.php","timestamp":1694078004966},{"id":"vHEE.php","timestamp":1694079937141},{"id":"GTM4.php","timestamp":1694079966965},{"id":"nwXp.php","timestamp":1694150657804},{"id":"CqZv.php","timestamp":1694150828703},{"id":"BlK3.php","timestamp":1694151332944},{"id":"FERW.php","timestamp":1694151921939},{"id":"Lijs.php","timestamp":1694152166653},{"id":"FEEX.php","timestamp":1694152248703},{"id":"qK2R.php","timestamp":1694152324664},{"id":"2f2N.php","timestamp":1694152510834},{"id":"EYsF.php","timestamp":1694155081248},{"id":"vMRw.php","timestamp":1694241791012},{"id":"Fy1M.php","timestamp":1694241842832},{"id":"uTnM.php","source":"undoRedo.source","timestamp":1694242171512},{"id":"W8Kd.php","timestamp":1694242189262},{"id":"O4Z9.php","timestamp":1694242227392},{"id":"Vzlb.php","timestamp":1694242255775}]}